docs_maker/__init__.py
docs_maker/__main__.py
docs_maker/cli/__init__.py
docs_maker/cli/argparse.py
docs_maker/cli/version.py
docs_maker/database/base.py
docs_maker/database/init_db_postgres.py
docs_maker/database/init_db_sqlite3.py
docs_maker/database/models/__init__.py
docs_maker/database/models/configurations.py
docs_maker/database/models/documents.py
docs_maker/database/services/__init__.py
docs_maker/database/services/config_service.py
docs_maker_gui/__init__.py
docs_maker_gui/__main__.py
docs_maker_gui/classes/CRUD.py
docs_maker_gui/classes/Configuration.py
docs_maker_gui/classes/LangSwitcher.py
docs_maker_gui/classes/MainWIndow.py
docs_maker_gui/classes/PageSwitcher.py
docs_maker_gui/classes/SetUpWidgets.py
docs_maker_gui/resources/icons/database-64-blue.svg
docs_maker_gui/resources/icons/home-64-blue.svg
docs_maker_gui/resources/icons/more-horiz-64-blue.svg
docs_maker_gui/resources/resources.py
docs_maker_gui/resources/resources.qrc
docs_maker_gui/ui/docs-maker-main-window.ui
docs_maker_gui/ui/docs_maker_main_window.py
docs_maker_messages/__init__.py
docs_maker_messages/en/LC_MESSAGES/messages.mo
docs_maker_messages/en/LC_MESSAGES/messages.po
docs_maker_messages/ru/LC_MESSAGES/messages.mo
docs_maker_messages/ru/LC_MESSAGES/messages.po
docs_maker-1.0.0.dev4.dist-info/METADATA
docs_maker-1.0.0.dev4.dist-info/WHEEL
docs_maker-1.0.0.dev4.dist-info/entry_points.txt
docs_maker-1.0.0.dev4.dist-info/RECORD
